setup.py
distributions/Binomialdistribution.py
distributions/Gaussiandistribution.py
distributions/Generaldistribution.py
distributions/__init__.py
distributions1999.egg-info/PKG-INFO
distributions1999.egg-info/SOURCES.txt
distributions1999.egg-info/dependency_links.txt
distributions1999.egg-info/not-zip-safe
distributions1999.egg-info/top_level.txt